README.md
setup.py
data_transformer/__init__.py
data_transformer/data_transformer.py
python_data_transformer.egg-info/PKG-INFO
python_data_transformer.egg-info/SOURCES.txt
python_data_transformer.egg-info/dependency_links.txt
python_data_transformer.egg-info/not-zip-safe
python_data_transformer.egg-info/top_level.txt