Metadata-Version: 2.1
Name: python-data-transformer
Version: 2020.4.9
Summary: Преобразователь/десериализатор данных из текста
Home-page: https://github.com/pavelmaksimov/python-data-transformer
Author: Pavel Maksimov
Author-email: vur21@ya.ru
License: MIT
Keywords: data,transform,transformer,desirialize,json
Platform: UNKNOWN
